how_to_use_poetry/__init__.py
how_to_use_poetry-0.1.0.dist-info/WHEEL
how_to_use_poetry-0.1.0.dist-info/METADATA
how_to_use_poetry-0.1.0.dist-info/RECORD
